rawdump/__init__.py
rawdump/__main__.py
rawdump/admin_shell.py
rawdump/handlers.py
rawdump/rawsocket.py
tests/__init__.py
tests/test_rawdump.py
rawdump-0.2.0.dist-info/METADATA
rawdump-0.2.0.dist-info/WHEEL
rawdump-0.2.0.dist-info/entry_points.txt
rawdump-0.2.0.dist-info/top_level.txt
rawdump-0.2.0.dist-info/RECORD
