Metadata-Version: 2.1
Name: rawdump
Version: 0.2.0
Summary: Dump tcp/ip packet by raw socket.
Home-page: https://github.com/drunkdream/rawdump
Author: drunkdream
Author-email: drunkdream@qq.com
License: MIT
Platform: UNKNOWN
Classifier: Development Status :: 3 - Alpha
Classifier: License :: OSI Approved :: MIT License
Classifier: Programming Language :: Python
Classifier: Programming Language :: Python :: 2
Classifier: Programming Language :: Python :: 2.7
Classifier: Programming Language :: Python :: 3
Classifier: Programming Language :: Python :: 3.4
Classifier: Programming Language :: Python :: 3.5
Classifier: Programming Language :: Python :: 3.6
Classifier: Programming Language :: Python :: 3.7
Classifier: Programming Language :: Python :: 3.8
Classifier: Intended Audience :: Developers
Requires-Python: >=2.7
Requires-Dist: netifaces ; sys_platform == "darwin"
Requires-Dist: pypcap ; sys_platform == "darwin"
Requires-Dist: pywin32 ; sys_platform == "win32"
